{
  "$schema": "https://developer.microsoft.com/json-schemas/fabric/item/report/definition/visualContainer/2.10.0/schema.json",
  "name": "b61e6c70b0372043b4be",
  "position": {
    "x": 944,
    "y": 96,
    "z": 16000,
    "height": 256,
    "width": 272,
    "tabOrder": 10000
  },
  "visual": {
    "visualType": "cardVisual",
    "query": {
      "queryState": {
        "Data": {
          "projections": [
            {
              "field": {
                "Measure": {
                  "Expression": {
                    "SourceRef": {
                      "Schema": "extension",
                      "Entity": "_KPI"
                    }
                  },
                  "Property": "CA Monde Année"
                }
              },
              "queryRef": "_KPI.CA Monde Année",
              "nativeQueryRef": "CA Monde",
              "displayName": "CA Monde"
            },
            {
              "field": {
                "Measure": {
                  "Expression": {
                    "SourceRef": {
                      "Schema": "extension",
                      "Entity": "_KPI"
                    }
                  },
                  "Property": "Prog CA non Comparable Année"
                }
              },
              "queryRef": "_KPI.Prog CA non Comparable Année",
              "nativeQueryRef": "Prog CA non comparable",
              "displayName": "Prog CA non comparable"
            }
          ]
        }
      },
      "sortDefinition": {
        "sort": [
          {
            "field": {
              "Measure": {
                "Expression": {
                  "SourceRef": {
                    "Schema": "extension",
                    "Entity": "_KPI"
                  }
                },
                "Property": "CA Monde Année"
              }
            },
            "direction": "Descending"
          }
        ],
        "isDefaultSort": true
      }
    },
    "objects": {
      "layout": [
        {
          "properties": {
            "orientation": {
              "expr": {
                "Literal": {
                  "Value": "1D"
                }
              }
            },
            "rowCount": {
              "expr": {
                "Literal": {
                  "Value": "2L"
                }
              }
            },
            "autoGrid": {
              "expr": {
                "Literal": {
                  "Value": "true"
                }
              }
            }
          }
        },
        {
          "properties": {
            "paddingUniform": {
              "expr": {
                "Literal": {
                  "Value": "0L"
                }
              }
            }
          },
          "selector": {
            "id": "default"
          }
        }
      ],
      "value": [
        {
          "properties": {
            "horizontalAlignment": {
              "expr": {
                "Literal": {
                  "Value": "'center'"
                }
              }
            },
            "fontSize": {
              "expr": {
                "Literal": {
                  "Value": "40D"
                }
              }
            }
          },
          "selector": {
            "id": "default"
          }
        },
        {
          "properties": {
            "fontSize": {
              "expr": {
                "Literal": {
                  "Value": "24D"
                }
              }
            }
          },
          "selector": {
            "metadata": "_KPI.Prog CA non Comparable Année"
          }
        }
      ],
      "label": [
        {
          "properties": {
            "fontSize": {
              "expr": {
                "Literal": {
                  "Value": "14D"
                }
              }
            }
          },
          "selector": {
            "id": "default"
          }
        },
        {
          "properties": {
            "fontSize": {
              "expr": {
                "Literal": {
                  "Value": "11D"
                }
              }
            }
          },
          "selector": {
            "metadata": "_KPI.Prog CA non Comparable Année"
          }
        }
      ]
    },
    "visualContainerObjects": {
      "title": [
        {
          "properties": {
            "text": {
              "expr": {
                "Literal": {
                  "Value": "'Vision Année'"
                }
              }
            },
            "alignment": {
              "expr": {
                "Literal": {
                  "Value": "'center'"
                }
              }
            },
            "fontSize": {
              "expr": {
                "Literal": {
                  "Value": "16D"
                }
              }
            }
          }
        }
      ]
    },
    "drillFilterOtherVisuals": true
  }
}